{
  "beautybebo":{
    "hair":[
      {
        "image_url":
            "https://www.beautybebo.com/pub/media/catalog/product/cache/37253e89591b79b38c00254331932999/f/6/f658864trese00000061_1.jpg",
        "name": "Tresemme Pro Pure Damage Recovery Shampoo & Mask Combo",
        "price": 1160,
        "off": 7,
        "strikedoffprice": 1200,
        "brand":"Tresemme"
    },
    {
        "image_url":
            "https://www.beautybebo.com/pub/media/catalog/product/cache/37253e89591b79b38c00254331932999/9/f/9f5a0dd8901248154192_1.jpg",
        "name": "Boroplus Aloe Vera Gel With Green Tea",
        "price": 360,
        "brand":"Boroplus"
    },
    {
        "image_url":
            "https://www.beautybebo.com/pub/media/catalog/product/cache/37253e89591b79b38c00254331932999/9/3/93d343en_3401344957253-01.jpg",
        "name": " Bioderma Node Ds+ Shampooing Anti-Dandruff Intense Shampoo",
        "price": 1527,
        "off": 5,
        "strikedoffprice": 1607,
        "brand":"Bioderma"
  
    },
    {
        "image_url":
            "https://www.beautybebo.com/pub/media/catalog/product/cache/37253e89591b79b38c00254331932999/e/9/e9c4ccctrese00000051_1.jpg",
        "name": "Tresemme Propure Moisture Boost - Shampoo + Mask + Serum Combo",
        "price": 1488,
        "off": 7,
        "strikedoffprice": 1600,
        "brand":"Tresemme"
    },
    {
        "image_url":
            "https://www.beautybebo.com/pub/media/catalog/product/cache/37253e89591b79b38c00254331932999/1/d/1d6accctrese00000049_1.jpg",
        "name": "Tresemme Propure Moisture Boost - Shampoo + Conditioner + Serum",
        "price": 1300,
        "off": 7,
        "strikedoffprice": 1400,
        "brand":"Tresemme"
    },
    {
        "image_url":
            "https://www.beautybebo.com/pub/media/catalog/product/cache/37253e89591b79b38c00254331932999/1/d/1d6accctrese00000049_1.jpg",
        "name": "Tresemme Pro Pure Damage Recovery - Shampoo + Mask + Serum Combo",
        "price": 1488,
        "off": 7,
        "strikedoffprice": 1600,
        "brand":"Tresemme"
    },
    {
        "image_url":
            "https://www.beautybebo.com/pub/media/catalog/product/cache/37253e89591b79b38c00254331932999/f/d/fd3cfb5trese00000046_1.jpg",
        "name": "Tresemme Pro Pure Damage Recovery - Shampoo + Conditioner + Serum ",
        "price": 1300,
        "off": 7,
        "strikedoffprice": 1400,
        "brand":"Tresemme"
    },
    {
        "image_url":
            "https://www.beautybebo.com/pub/media/catalog/product/cache/37253e89591b79b38c00254331932999/0/a/0a37fb5trese00000047_1.jpg",
        "name": "Tresemme Pro Pure Moisture Boost Serum With Aloe Essence Sulphate",
        "price": 400,
        "brand":"Tresemme"
    },
    {
        "image_url":
            "https://www.beautybebo.com/pub/media/catalog/product/cache/37253e89591b79b38c00254331932999/9/c/9cc7fb5trese00000045_1.jpg",
        "name": "Tresemme Pro Pure Moisture Boost Mask With Aloe Essence Sulphate Free",
        "price": 651,
        "off": 7,
        "strikedoffprice": 700,
        "brand":"Tresemme"
    },
    {
        "image_url":
            "https://www.beautybebo.com/pub/media/catalog/product/cache/37253e89591b79b38c00254331932999/6/6/6644a8ctrese00000044_1.jpg",
        "name": "Tresemme Pro Pure Moisture Boost Conditioner With Aloe Essence",
        "price": 465,
        "off": 7,
        "strikedoffprice": 500,
        "brand":"Tresemme"
    },
    {
        "image_url":
            "https://www.beautybebo.com/pub/media/catalog/product/cache/37253e89591b79b38c00254331932999/6/6/6644a8ctrese00000044_1.jpg",
        "name": "Tresemme Pro Pure Moisture Boost Shampoo With Aloe Essence Sulphate",
        "price": 465,
        "off": 7,
        "strikedoffprice": 500,
        "brand":"Tresemme"
    },
    {
        "image_url":
            "https://www.beautybebo.com/pub/media/catalog/product/cache/37253e89591b79b38c00254331932999/3/0/30cb3d88901030871252_1.jpg",
        "name": "Tresemme Keratin Smooth Hair Serum",
        "price": 350,
        "brand":"Tresemme"
    },
    {
        "image_url":
            "https://www.beautybebo.com/pub/media/catalog/product/cache/37253e89591b79b38c00254331932999/e/9/e91dfb5trese00000042_1.jpg",
        "name": "Tresemme Pro Pure Damage Recovery Serum With Fermented Rice Water",
        "price": 400,
        "brand":"Tresemme"
    },
    {
        "image_url":
            "https://www.beautybebo.com/pub/media/catalog/product/cache/37253e89591b79b38c00254331932999/8/b/8b11fb5trese00000043_1.jpg",
        "name": "Tresemme Pro Pure Damage Recovery Mask With Fermented Rice Water",
        "price": 651,
        "off": 7,
        "strikedoffprice": 700,
        "brand":"Tresemme"
    },
    {
        "image_url":
            "https://www.beautybebo.com/pub/media/catalog/product/cache/37253e89591b79b38c00254331932999/0/9/0924fb5trese00000041_1.jpg",
        "name": "Tresemme Pro Pure Damage Recovery Conditioner Fermented Rice Water",
        "price": 465,
        "off": 7,
        "strikedoffprice": 500,
        "brand":"Tresemme"
    },
    {
        "image_url":
            "https://www.beautybebo.com/pub/media/catalog/product/cache/37253e89591b79b38c00254331932999/8/e/8e0ca8ctrese00000040_1.jpg",
        "name": "Tresemme Pro Pure Damage Recovery Shampoo With Fermented Rice Water",
        "price": 465,
        "off": 7,
        "strikedoffprice": 500,
        "brand":"Tresemme"
    },
    {
        "image_url":
            "https://www.beautybebo.com/pub/media/catalog/product/cache/37253e89591b79b38c00254331932999/3/c/3cabc5a8901030805080_2.jpg",
        "name": "Sunsilk Almond & Honey Shampoo",
        "price": 315,
        "brand":"Sunsilk"
    },
    {
        "image_url":
            "https://www.beautybebo.com/pub/media/catalog/product/cache/37253e89591b79b38c00254331932999/8/c/8c9c39226479_s1-8901030897429.jpg",
        "name": "Indulekha Bringha Hair Strengthening Lepam",
        "price": 603,
        "off": 7,
        "strikedoffprice": 648,
        "brand":"Indulekha"
    },
    {
        "image_url":
            "https://www.beautybebo.com/pub/media/catalog/product/cache/37253e89591b79b38c00254331932999/7/a/7ab36558901088159562_7.jpeg",
        "name": "Livon Super Styler Hair Serum For Women & Men For Hair Straightening",
        "price": 375,
        "brand":"Livon"
  
    },
    {
        "image_url":
            "https://www.beautybebo.com/pub/media/catalog/product/cache/37253e89591b79b38c00254331932999/4/9/4902430773829_2__1.jpg",
        "name": "Head & Shoulders Cool Menthol Anti-Dandruff Shampoo",
        "price": 300,
        "off": 7,
        "strikedoffprice": 315,
        "brand":"Head and Shoulders"
  
    },
    {
        "image_url":
            "https://www.beautybebo.com/pub/media/catalog/product/cache/37253e89591b79b38c00254331932999/8/c/8c2e07e205000000436877.jpg",
        "name": "Shahnaz Husain Hair Touch-Up Plus - Brown",
        "price": 302,
        "off": 10,
        "strikedoffprice": 335,
        "brand":"Shahnaz"
    },
    {
        "image_url":
            "https://www.beautybebo.com/pub/media/catalog/product/cache/37253e89591b79b38c00254331932999/2/3/23e539226478_s1-8901030897436.jpg",
        "name": "Indulekha Bringha Hair Strengthening Serum",
        "price": 718,
        "off": 10,
        "strikedoffprice": 756,
        "brand":"Indulekha"
    },
    {
        "image_url":
            "https://www.beautybebo.com/pub/media/catalog/product/cache/37253e89591b79b38c00254331932999/2/a/2ae55ce4902430871464.jpg",
        "name": "Head & Shoulders Cool Menthol 2-In-1 Anti-Dandruff Shampoo + Conditioner - 650ml",
        "price": 805,
        "off": 8,
        "strikedoffprice": 875,
        "brand":"Head and Shoulders"
  
    },
    {
        "image_url":
            "https://www.beautybebo.com/pub/media/catalog/product/cache/37253e89591b79b38c00254331932999/6/b/6b028414987176112545.jpg",
        "name": "Head & Shoulders 2-In-1 Anti-Hairfall Anti-Dandruff Shampoo + Conditioner",
        "price": 338,
        "off": 10,
        "strikedoffprice": 375,
        "brand":"Head and Shoulders"
        
  
    },
    {
        "image_url":
            "https://www.beautybebo.com/pub/media/catalog/product/cache/37253e89591b79b38c00254331932999/f/e/fe332d68907122014729_1.jpg ",
        "name": "Vlcc Onion & Fenugreek Conditioner",
        "price": 299,
        "brand":"Vlcc"
    },
    {
        "image_url":
            "https://www.beautybebo.com/pub/media/catalog/product/cache/37253e89591b79b38c00254331932999/5/d/5d762d68907122014736_1.jpg",
        "name": "Vlcc Onion & Fenugreek Hair Oil",
        "price": 399,
        "brand":"Vlcc"
    },
    {
        "image_url":
            "https://www.beautybebo.com/pub/media/catalog/product/cache/37253e89591b79b38c00254331932999/f/4/f4342d68907122014712_1.jpg",
        "name": "Vlcc Onion & Fenugreek Shampoo",
        "price": 374,
        "off": 12,
        "strikedoffprice": 425,
        "brand":"Vlcc"
    },
    {
        "image_url":
            "https://www.beautybebo.com/pub/media/catalog/product/cache/37253e89591b79b38c00254331932999/8/c/8c4225a8904086320842_2.jpg",
        "name": "Vega Hot Curl Brush - Large (H1-Prl)",
        "price": 899,
        "off": 10,
        "strikedoffprice": 999,
        "brand":"Vega"
    },
    {
        "image_url":
            "https://www.beautybebo.com/pub/media/catalog/product/cache/37253e89591b79b38c00254331932999/1/c/1cb925avegax00000041_1.jpg",
        "name": "Vega Multi-Styler Hair Brush & Hair Dryer Keratin Infused Coating & Anti-Static Bristles, (VHSD-01)",
        "price": 2613,
        "off": 5,
        "strikedoffprice": 2750,
        "brand":"Vega"
    },
    {
        "image_url":
            "https://www.beautybebo.com/pub/media/catalog/product/cache/37253e89591b79b38c00254331932999/d/3/d39a25avegax00000027_1.jpg",
        "name": "Vega K-Shine Hair Straightener(Vhsh-28)",
        "price": 1208,
        "off": 5,
        "strikedoffprice": 1299,
        "brand":"Vega"
    },
    {
        "image_url":
            "https://www.beautybebo.com/pub/media/catalog/product/cache/37253e89591b79b38c00254331932999/9/e/9ee625avegax00000026_1.jpg",
        "name": "Vega Go-Pro 2100 Hair Dryer(Vhdh-25)",
        "price": 1709,
        "off": 5,
        "strikedoffprice": 1799,
        "brand":"Vega"
    },
    {
        "image_url":
            "https://www.beautybebo.com/pub/media/catalog/product/cache/37253e89591b79b38c00254331932999/7/2/72e225a8904086321191_0.jpg",
        "name": "Vega Hot Curl Brush - Big (E16-Prb)",
        "price": 446,
        "off": 15,
        "strikedoffprice": 525,
        "brand":"Vega"
    },
    {
        "image_url":
            "https://www.beautybebo.com/pub/media/catalog/product/cache/37253e89591b79b38c00254331932999/b/1/b12825avegax00000046_1.jpg",
        "name": "VEGA Black Shine Hair Straightening Brush With Ionic Technology & 16 Temprature Settings (VHSB-04)",
        "price": 2374,
        "off": 5,
        "strikedoffprice": 2499,
        "brand":"Vega"
    },
    {
        "image_url":
            "https://www.beautybebo.com/pub/media/catalog/product/cache/37253e89591b79b38c00254331932999/b/9/b98825avegax00000042_1.jpg",
        "name": "Vega K-Glam 3 In 1 Hair Styler - Rose Gold (Vhscc-04)",
        "price": 2184,
        "strikedoffprice": 2299,
        "brand":"Vega"
    },
    {
        "image_url":
            "https://www.beautybebo.com/pub/media/catalog/product/cache/37253e89591b79b38c00254331932999/4/c/4c8425a8904086303180_1.jpg",
        "name": "Vega 3-In-1 Keratin Hair Styler (Vhscc-03) - Rose Gold",
        "price": 2089,
        "off": 5,
        "strikedoffprice": 2199,
        "brand":"Vega"
    },
    {
        "image_url":
            "https://www.beautybebo.com/pub/media/catalog/product/cache/37253e89591b79b38c00254331932999/5/9/596225avegax00000009_1.jpg",
        "name": "Vega I-Wave Hair Waver(Vhwr-01)",
        "price": 1899,
        "off": 5,
        "strikedoffprice": 1999,
        "brand":"Vega"
    },
    {
        "image_url":
            "https://www.beautybebo.com/pub/media/catalog/product/cache/37253e89591b79b38c00254331932999/c/6/c65525avegax00000003_1.jpg",
        "name": "Vega Vhth 16 Beard Trimmer",
        "price": 1394,
        "off": 7,
        "strikedoffprice": 1499,
        "brand":"Vega"
    },
    {
        "image_url":
            "https://www.beautybebo.com/pub/media/catalog/product/cache/37253e89591b79b38c00254331932999/d/5/d55b25avegax00000085_1.jpg",
        "name": "Vega Go Glam Hair Straightener With Titanium Plates & 3 Temperature",
        "price": 1899,
        "off": 5,
        "strikedoffprice": 1999,
        "brand":"Vega"
    },
    {
        "image_url":
            "https://www.beautybebo.com/pub/media/catalog/product/cache/37253e89591b79b38c00254331932999/f/7/f70525a8904086395291_0.jpg",
        "name": "Vega Self-Style Flat Hair Straightener (Vhsh-27)",
        "price": 1471,
        "off": 8,
        "strikedoffprice": 1599,
        "brand":"Vega"
    }
    ]
  },


  "users": [
    {
      "id": 1,
      "first_name": "Ramanpreet",
      "last_name": "Singh",
      "email": "admin@gmail.com",
      "gender": "Male",
      "password": "admin"
    }
  ],
  "medisons": [
    {
      "id": 1,
      "productname": "Dorzox Eye Drops 5ml",
      "price": "390.18",
      "MRP": "459.03",
      "offer": "15",
      "description": "5ml Eye Drop in Bottle",
      "contains": "Dorzolamid / Dorzolamide(2.0 %)",
      "therapy": "GLAUCOMA DRUGS",
      "uses": "",
      "side_effects": "",
      "Brand": "DORZOX",
      "Expiry": "29/04/2024",
      "prescription": "no",
      "img1": "https://cdn01.pharmeasy.in/dam/products/060175/dorzox-eye-drops-5ml-1-1641535227.jpg?dim=320x320&dpr=1&q=100",
      "img2": "https://cdn01.pharmeasy.in/dam/products/060175/dorzox-eye-drops-5ml-2-1641535223.jpg",
      "img3": "https://cdn01.pharmeasy.in/dam/products/060175/dorzox-eye-drops-5ml-3-1641535224.jpg",
      "manufacturer": "CIPLA LIMITED",
      "quantity": 1
    },
    {
      "id": 2,
      "productname": "Ecosprin 75mg Strip Of 14 Tablets",
      "price": "4.53",
      "MRP": "5.33",
      "offer": "15",
      "description": "14 Tablet(s) in Strip",
      "contains": "Aspirin / Acetyl Salicylic Acid(75.0 Mg)",
      "therapy": "ANTI-PLATELET",
      "uses": "Prevention of heart attack, stroke, angina",
      "side_effects": "Indigestion, nausea, diarrhoea, vomiting",
      "Brand": "Ecosprin ",
      "Expiry": "28/02/2024",
      "prescription": "no",
      "img1": "https://cdn01.pharmeasy.in/dam/products/064425/ecosprin-75mg-strip-of-14-tablets-1-1647434835.jpg?dim=320x320&dpr=1&q=100",
      "img2": "https://cdn01.pharmeasy.in/dam/products/064425/ecosprin-75mg-strip-of-14-tablets-2-1647434829.jpg",
      "img3": "https://cdn01.pharmeasy.in/dam/products/064425/ecosprin-75mg-strip-of-14-tablets-3-1647434825.jpg",
      "manufacturer": "USV PVT LTD",
      "quantity": 1
    },
    {
      "id": 3,
      "productname": "Teplota 100mg Bottle Of 15ml Syrup",
      "price": "22.95",
      "MRP": "27.00",
      "offer": "15",
      "description": "15ml Syrup in Bottle",
      "contains": "Paracetamol / Acetaminophen(100.0 Mg)",
      "therapy": "ANALGESIC/ANTIPYRETIC",
      "Brand": "TEPLOTA",
      "uses": "",
      "side_effects": "",
      "Expiry": "28/02/2024",
      "prescription": "no",
      "img1": "https://cdn01.pharmeasy.in/dam/products/W38967/teplota-100mg-bottle-of-15ml-syrup-1-1661333432.jpg?dim=320x320&dpr=1&q=100",
      "img2": "https://cdn01.pharmeasy.in/dam/products/W38967/teplota-100mg-bottle-of-15ml-syrup-2-1661333427.jpg",
      "img3": "https://cdn01.pharmeasy.in/dam/products/W38967/teplota-100mg-bottle-of-15ml-syrup-6.2-1661333389.jpg",
      "manufacturer": "AVIGHNA MEDICARE PVT LTD",
      "quantity": 1
    },
    {
      "id": 4,
      "productname": "Dolo 500mg Tablet",
      "price": "14.42",
      "MRP": "16.96",
      "offer": "15",
      "description": "15 Tablet(s) in Strip",
      "contains": "Paracetamol / Acetaminophen(500.0 Mg)",
      "therapy": "ANALGESIC/ANTIPYRETIC",
      "uses": "Fever and pain",
      "side_effects": "Skin rash, itching, blisters",
      "Brand": "DOLO",
      "Expiry": "30/05/2026",
      "prescription": "no",
      "img1": "https://cdn01.pharmeasy.in/dam/products/192033/dolo-500mg-tablet-2-1641532606.jpg?dim=320x320&dpr=1&q=100",
      "img2": "https://cdn01.pharmeasy.in/dam/products/192033/dolo-500mg-tablet-7-1641532605.jpg",
      "img3": "https://cdn01.pharmeasy.in/dam/products/192033/dolo-500mg-tablet-2-1641532606.jpg?dim=320x320&dpr=1&q=100",
      "manufacturer": "MICRO LABS",
      "quantity": 1
    },
    {
      "id": 5,
      "productname": "Dolo 650mg Strip Of 15 Tablets",
      "price": "29.13",
      "MRP": "34.27",
      "offer": "15",
      "description": "15 Tablet(s) in Strip",
      "contains": "Paracetamol / Acetaminophen(650.0 Mg)",
      "therapy": "ANALGESIC/ANTIPYRETIC",
      "uses": "Pain and fever",
      "side_effects": "Skin rash, itching, blisters",
      "Brand": "DOLO",
      "Expiry": "30/05/2026",
      "prescription": "no",
      "img1": "https://cdn01.pharmeasy.in/dam/products/059346/dolo-650mg-strip-of-15-tablets-2-1653986150.jpg?dim=320x320&dpr=1&q=100",
      "img2": "https://cdn01.pharmeasy.in/dam/products/059346/dolo-650mg-strip-of-15-tablets-3-1653986087.jpg",
      "img3": "https://cdn01.pharmeasy.in/dam/products/059346/dolo-650mg-strip-of-15-tablets-7-1653986144.jpg",
      "manufacturer": "MICRO LABS",
      "quantity": 1
    },
    {
      "id": 6,
      "productname": "Dolonex Dt 20 Strip Of 15 Tablets",
      "price": "183.45",
      "MRP": "215.82",
      "offer": "15",
      "description": "15 Tablet(s) in Strip",
      "contains": "Piroxicam(20.0 Mg)",
      "therapy": "DRUGS FOR OSTEOARTHRITIS",
      "uses": "Pain, inflammation",
      "side_effects": "Nausea, vomiting, stomach upset, indigestion",
      "Brand": "DOLONEX",
      "Expiry": "29/06/2025",
      "prescription": "yes",
      "img1": "https://cdn01.pharmeasy.in/dam/products/I04304/dolonex-dt-20-strip-of-15-tablets-2-1641536751.jpg?dim=320x320&dpr=1&q=100",
      "img2": "https://cdn01.pharmeasy.in/dam/products/I04304/dolonex-dt-20-strip-of-15-tablets-7-1641536750.jpg",
      "img3": "https://cdn01.pharmeasy.in/dam/products/I04304/dolonex-dt-20-strip-of-15-tablets-2-1641536751.jpg?dim=320x320&dpr=1&q=100",
      "manufacturer": "PFIZER LTD",
      "quantity": 1
    },
    {
      "id": 7,
      "productname": "Dolopar 650mg Strip Of 15 Tablets",
      "price": "26.27",
      "MRP": "30.91",
      "offer": "15",
      "description": "15 Tablet(s) in Strip",
      "contains": "Paracetamol / Acetaminophen(650.0 Mg)",
      "therapy": "ANALGESIC/ANTIPYRETIC",
      "uses": "Pain and fever",
      "side_effects": "Skin rash, itching, blisters",
      "Brand": "DOLOPAR",
      "Expiry": "27/02/2026",
      "prescription": "no",
      "img1": "https://cdn01.pharmeasy.in/dam/products/269216/dolopar-650mg-strip-of-15-tablets-1-1641533687.jpg?dim=320x320&dpr=1&q=100",
      "img2": "https://cdn01.pharmeasy.in/dam/products/269216/dolopar-650mg-strip-of-15-tablets-2-1641533682.jpg",
      "img3": "https://cdn01.pharmeasy.in/dam/products/269216/dolopar-650mg-strip-of-15-tablets-4-1641533686.jpg",
      "manufacturer": "MICRO LABS",
      "quantity": 1
    },
    {
      "id": 8,
      "productname": "Dolowin Plus Tablet",
      "price": "63.75",
      "MRP": "75.00",
      "offer": "15",
      "description": "10 Tablet(s) in Strip",
      "contains": "Aceclofenac(100.0 Mg) + Paracetamol / Acetaminophen(500.0 Mg)",
      "therapy": "ANALGESIC/ANTIPYRETIC",
      "uses": "Pain, inflammation",
      "side_effects": "Nausea, vomiting, stomach upset, indigestion",
      "Brand": "DOLOWIN PLUS",
      "Expiry": "30/01/2025",
      "prescription": "yes",
      "img1": "https://cdn01.pharmeasy.in/dam/products/059610/dolowin-plus-tablet-2-1641535977.jpg?dim=320x320&dpr=1&q=100",
      "img2": "https://cdn01.pharmeasy.in/dam/products/059610/dolowin-plus-tablet-7-1641535978.jpg",
      "img3": "https://cdn01.pharmeasy.in/dam/products/059610/dolowin-plus-tablet-2-1641535977.jpg?dim=320x320&dpr=1&q=100",
      "manufacturer": "MICRO LABS",
      "quantity": 1
    },
    {
      "id": 9,
      "productname": "Dolokind Plus Strip Of 15 Tablets",
      "price": "52.95",
      "MRP": "62.29",
      "offer": "15",
      "description": "15 Tablet(s) in Strip",
      "contains": "Aceclofenac(100.0 Mg) + Paracetamol / Acetaminophen(325.0 Mg)",
      "therapy": "ANALGESIC/ANTIPYRETIC",
      "uses": "",
      "side_effects": "",
      "Brand": "DOLOKIND",
      "Expiry": "29/04/2024",
      "prescription": "no",
      "img1": "https://cdn01.pharmeasy.in/dam/products/I48369/dolokind-plus-strip-of-15-tablets-1-1648475636.jpg?dim=320x320&dpr=1&q=100",
      "img2": "https://cdn01.pharmeasy.in/dam/products/I48369/dolokind-plus-strip-of-15-tablets-7-1648475638.jpg",
      "img3": "https://cdn01.pharmeasy.in/dam/products/I48369/dolokind-plus-strip-of-15-tablets-1-1648475636.jpg?dim=320x320&dpr=1&q=100",
      "manufacturer": "MANKIND PHARMACEUTICALS LTD",
      "quantity": 1
    },
    {
      "id": 10,
      "productname": "Dolopar 250mg Suspension 60ml",
      "price": "38.14",
      "MRP": "44.35",
      "offer": "15",
      "description": "60ml Suspension in Bottle",
      "contains": "Paracetamol / Acetaminophen(250.0 Mg/5ml)",
      "therapy": "ANALGESIC/ANTIPYRETIC",
      "uses": "Fever, Pain",
      "side_effects": "Rash, Nausea",
      "Brand": "DOLOPAR",
      "Expiry": "30/12/2024",
      "prescription": "no",
      "img1": "https://cdn01.pharmeasy.in/dam/products/059570/dolopar-250mg-suspension-60ml-2-1641535619.jpg?dim=320x320&dpr=1&q=100",
      "img2": "https://cdn01.pharmeasy.in/dam/products/059570/dolopar-250mg-suspension-60ml-6-1641535618.jpg",
      "img3": "https://cdn01.pharmeasy.in/dam/products/059570/dolopar-250mg-suspension-60ml-7-1641535617.jpg",
      "manufacturer": "MICRO LABS",
      "quantity": 1
    },
    {
      "id": 11,
      "productname": "Dologel Gel 15gm",
      "price": "84.36",
      "MRP": "99.25",
      "offer": "15",
      "description": "15g Mouth Gel in Tube",
      "contains": "Choline Salicylate(8.7 %) + Lidocaine / Lignocaine(2.0 %)",
      "therapy": "",
      "uses": "Mouth ulcers",
      "side_effects": "Buring, itching, readness at application site.",
      "Brand": "DOLOGEL",
      "Expiry": "30/08/2024",
      "prescription": "no",
      "img1": "https://cdn01.pharmeasy.in/dam/products/059430/dologel-gel-15gm-1-1641535618.jpg?dim=320x320&dpr=1&q=100",
      "img2": "https://cdn01.pharmeasy.in/dam/products/059430/dologel-gel-15gm-2-1641535616.jpg",
      "img3": "https://cdn01.pharmeasy.in/dam/products/059430/dologel-gel-15gm-4-1641535620.jpg",
      "manufacturer": "DR REDDY'S LABORATORIES LTD",
      "quantity": 1
    },
    {
      "id": 12,
      "productname": "Dolo Drops",
      "price": "25.56",
      "MRP": "30.07",
      "offer": "15",
      "description": "15ml Oral Drop in Bottle",
      "contains": "Paracetamol / Acetaminophen(100.0 Mg/Ml)",
      "therapy": "ANALGESIC/ANTIPYRETIC",
      "uses": "Fever and pain",
      "side_effects": "Skin rash, itching, blisters, allergic reaction",
      "Brand": "DOLO",
      "Expiry": "30/05/2024",
      "prescription": "no",
      "img1": "https://cdn01.pharmeasy.in/dam/products/192032/dolo-drops-1-1641533671.jpg?dim=320x320&dpr=1&q=100",
      "img2": "https://cdn01.pharmeasy.in/dam/products/192032/dolo-drops-2-1641533668.jpg",
      "img3": "https://cdn01.pharmeasy.in/dam/products/192032/dolo-drops-3-1641533670.jpg",
      "manufacturer": "MICRO LABS",
      "quantity": 1
    },
    {
      "id": 13,
      "productname": "Dolokind Mr Strip Of 10 Tablets",
      "price": "63.75",
      "MRP": "75.00",
      "offer": "15",
      "description": "10 Tablet(s) in Strip",
      "contains": "Chlorzoxazone(250.0 Mg) + Aceclofenac(100.0 Mg) + Paracetamol / Acetaminophen(325.0 Mg)",
      "therapy": "ANALGESIC/ANTIPYRETIC",
      "uses": "Muscles and joint pain",
      "side_effects": "Dizziness, lightheadedness, nausea, vomiting, weakness",
      "Brand": "DOLOKIND",
      "Expiry": "30/07/2024",
      "prescription": "yes",
      "img1": "https://cdn01.pharmeasy.in/dam/products/Y97120/doloend-mr-strip-of-10-tablets-1-1641538974.jpg?dim=320x320&dpr=1&q=100",
      "img2": "https://cdn01.pharmeasy.in/dam/products/Y97120/doloend-mr-strip-of-10-tablets-3-1641538976.jpg",
      "img3": "https://cdn01.pharmeasy.in/dam/products/Y97120/doloend-mr-strip-of-10-tablets-4-1641538972.jpg",
      "manufacturer": "MANKIND PHARMACEUTICALS LTD",
      "quantity": 1
    },
    {
      "id": 14,
      "productname": "Doloforce Dt 20mg Strip Of 10 Tablets",
      "price": "58.70",
      "MRP": "69.06",
      "offer": "15",
      "description": "10 Tablet(s) in Strip",
      "contains": "Piroxicam(20.0 Mg)",
      "therapy": "DRUGS FOR OSTEOARTHRITIS",
      "uses": "Pain and inflammation",
      "side_effects": "Dizziness, drowsiness, stomach pain, diarrhoea",
      "Brand": "DOLOFORCE",
      "Expiry": "30/05/2024",
      "prescription": "yes",
      "img1": "https://cdn01.pharmeasy.in/dam/products/I00435/doloforce-dt-20mg-strip-of-10-tablets-2-1648473744.jpg?dim=320x320&dpr=1&q=100",
      "img2": "https://cdn01.pharmeasy.in/dam/products/I00435/doloforce-dt-20mg-strip-of-10-tablets-7-1648473746.jpg",
      "img3": "https://cdn01.pharmeasy.in/dam/products/I00435/doloforce-dt-20mg-strip-of-10-tablets-2-1648473744.jpg?dim=320x320&dpr=1&q=100",
      "manufacturer": "MANKIND PHARMACEUTICALS LTD",
      "quantity": 1
    },
    {
      "id": 15,
      "productname": "Dolowin Mr Strip Of 10 Tablets",
      "price": "82.45",
      "MRP": "97.00",
      "offer": "15",
      "description": "10 Tablet(s) in Strip",
      "contains": "Chlorzoxazone(250.0 Mg) + Aceclofenac(100.0 Mg) + Paracetamol / Acetaminophen(325.0 Mg)",
      "therapy": "ANALGESIC/ANTIPYRETIC",
      "uses": "Muscles and joint pain",
      "side_effects": "Dizziness, lightheadedness, nausea, vomiting, weakness",
      "Brand": "DOLOWIN",
      "Expiry": "30/07/2024",
      "prescription": "no",
      "img1": "https://cdn01.pharmeasy.in/dam/products/192038/dolowin-mr-strip-of-10-tablets-2-1641533668.jpg?dim=320x320&dpr=1&q=100",
      "img2": "https://cdn01.pharmeasy.in/dam/products/192038/dolowin-mr-strip-of-10-tablets-7-1641533669.jpg",
      "img3": "https://cdn01.pharmeasy.in/dam/products/192038/dolowin-mr-strip-of-10-tablets-2-1641533668.jpg?dim=320x320&dpr=1&q=100",
      "manufacturer": "MICRO LABS",
      "quantity": 1
    },
    {
      "id": 16,
      "productname": "Dolocold Ds Syrup 60ml",
      "price": "52.23",
      "MRP": "61.45",
      "offer": "15",
      "description": "60ml Syrup in Bottle",
      "contains": "Chlorpheniramine Maleate(2.0 Mg) + Phenylephrine(5.0 Mg) + Paracetamol / Acetaminophen(250.0 Mg)",
      "therapy": "COUGH COLD PREPARATION",
      "uses": "Common cold and cough",
      "side_effects": "Headache, dizziness, nausea, fear feeling, anxiety",
      "Brand": "DOLOCOLD",
      "Expiry": "DOLOCOLD",
      "prescription": "yes",
      "img1": "https://cdn01.pharmeasy.in/dam/products/G81368/dolocold-ds-syrup-60ml-1-1652180655.jpg?dim=320x320&dpr=1&q=100",
      "img2": "https://cdn01.pharmeasy.in/dam/products/G81368/dolocold-ds-syrup-60ml-4-1652180460.jpg",
      "img3": "https://cdn01.pharmeasy.in/dam/products/G81368/dolocold-ds-syrup-60ml-2-1668001291.jpg",
      "manufacturer": "MICRO LABS",
      "quantity": 1
    },
    {
      "id": 17,
      "productname": "Dolostat Sp Tablet",
      "price": "42.50",
      "MRP": "50.00",
      "offer": "15",
      "description": "10 Tablet(s) in Strip",
      "contains": "Aceclofenac(100.0 Mg) + Serratiopeptidase(15.0 Mg) + Paracetamol / Acetaminophen(325.0 Mg)",
      "therapy": "ANALGESIC/ANTIPYRETIC",
      "uses": "Pain relief",
      "side_effects": "Nausea, vomiting, stomach pain, dizziness, indigestion",
      "Brand": "DOLOSTAT",
      "Expiry": "30/08/2024",
      "prescription": "no",
      "img1": "https://cdn01.pharmeasy.in/dam/products/224318/dolostat-sp-tablet-2-1641531175.jpg?dim=320x320&dpr=1&q=100",
      "img2": "https://cdn01.pharmeasy.in/dam/products/224318/dolostat-sp-tablet-7-1641531173.jpg",
      "img3": "https://cdn01.pharmeasy.in/dam/products/224318/dolostat-sp-tablet-2-1641531175.jpg?dim=320x320&dpr=1&q=100",
      "manufacturer": "BLUE CROSS LABORATORIES PRIVATE LIMITED",
      "quantity": 1
    },
    {
      "id": 18,
      "productname": "Roseday Gold 20mg Strip Of 10 Capsules",
      "price": "214.92",
      "MRP": "252.85",
      "offer": "15",
      "description": "10 Capsule(s) in Strip",
      "contains": "Rosuvastatin(20.0 Mg) + Clopidogrel(75.0 Mg) + Aspirin / Acetyl Salicylic Acid(75.0 Mg)",
      "therapy": "ANTI-PLATELET AND HYPOLIPIDEMIC DRUGS",
      "uses": "Heart attack, stroke, angina",
      "side_effects": "Nausea, vomiting, headache, muscle ache",
      "Brand": "ROSEDAY",
      "Expiry": "29/04/2024",
      "prescription": "yes",
      "img1": "https://cdn01.pharmeasy.in/dam/products/N11435/roseday-20mg-strip-of-15-tablets-6.1-1669357557.jpg?dim=320x320&dpr=1&q=100",
      "img2": "https://cdn01.pharmeasy.in/dam/products/N11435/roseday-20mg-strip-of-15-tablets-7-1669357698.jpg",
      "img3": "https://cdn01.pharmeasy.in/dam/products/N11435/roseday-20mg-strip-of-15-tablets-6.1-1669357557.jpg?dim=320x320&dpr=1&q=100",
      "manufacturer": "USV PVT LTD",
      "quantity": 1
    }
  ]
}